astraflux/__init__.py
astraflux/databases/__init__.py
astraflux/databases/_databases_api.py
astraflux/databases/_mongodb.py
astraflux/databases/_redisdb.py
astraflux/generateId/__init__.py
astraflux/generateId/_snowflake.py
astraflux/inject/__init__.py
astraflux/inject/inject_init.py
astraflux/interface/__init__.py
astraflux/interface/async_task.py
astraflux/interface/config_processing.py
astraflux/interface/databases_api.py
astraflux/interface/format_time.py
astraflux/interface/logger.py
astraflux/interface/mongodb.py
astraflux/interface/network.py
astraflux/interface/rabbitmq.py
astraflux/interface/redisdb.py
astraflux/interface/rpc.py
astraflux/interface/run.py
astraflux/interface/scheduler.py
astraflux/interface/snowflake.py
astraflux/logger/__init__.py
astraflux/logger/_logger.py
astraflux/meta/__init__.py
astraflux/meta/keys.py
astraflux/meta/meta.py
astraflux/mq/__init__.py
astraflux/mq/_rabbitmq.py
astraflux/rpc/__init__.py
astraflux/rpc/_rpc.py
astraflux/rpc/client.py
astraflux/scheduler/__init__.py
astraflux/scheduler/_async_task.py
astraflux/scheduler/_scheduler.py
astraflux/scheduler/cronparser.py
astraflux/servers/__init__.py
astraflux/servers/_run.py
astraflux/servers/build.py
astraflux/servers/run_server.py
astraflux/servers/run_worker.py
astraflux/settings/__init__.py
astraflux/settings/_config_processing.py
astraflux/utils/__init__.py
astraflux/utils/_format_time.py
astraflux/utils/_network.py
astraflux/workflows/__init__.py
astraflux/workflows/monitoring.py
astraflux/workflows/task_distribution.py
astraflux-1.0.9.dist-info/licenses/LICENSE
servers/__init__.py
astraflux-1.0.9.dist-info/METADATA
astraflux-1.0.9.dist-info/WHEEL
astraflux-1.0.9.dist-info/top_level.txt
astraflux-1.0.9.dist-info/RECORD
