Metadata-Version: 2.4
Name: astraflux
Version: 1.0.9
Summary: AstraFlux Description
Home-page: https://gitee.com/ZYPH/astra-flux
Author: YanPing
Author-email: zyphhxx@foxmail.com
Maintainer: YanPing
Maintainer-email: zyphhxx@foxmail.com
License: MIT License
Classifier: Development Status :: 3 - Alpha
Classifier: Intended Audience :: Developers
Classifier: Topic :: Software Development :: Build Tools
Classifier: License :: OSI Approved :: MIT License
Classifier: Programming Language :: Python :: 3
Requires-Python: >=3.8
License-File: LICENSE
Requires-Dist: psutil
Requires-Dist: pika
Requires-Dist: pytz
Requires-Dist: pymongo
Requires-Dist: pyyaml
Requires-Dist: redis
Dynamic: author
Dynamic: author-email
Dynamic: classifier
Dynamic: description
Dynamic: home-page
Dynamic: license
Dynamic: license-file
Dynamic: maintainer
Dynamic: maintainer-email
Dynamic: requires-dist
Dynamic: requires-python
Dynamic: summary
